{
  "$schema": "https://mintlify.com/schema.json",
  "name": "Entity Matcher",
  "logo": {
    "dark": "/logo/entity_match_logo.png",
    "light": "/logo/entity_match_logo.png"
  },
  "favicon": "/logo/entity_match_logo.png",
  "colors": {
    "primary": "#41c8d0",
    "light": "#41c8d0",
    "dark": "#41c8d0",
    "anchors": {
      "from": "#41c8d0",
      "to": "#fb5672"
    }
  },
  "openapi": "https://www.entitymatcher.com/api/v1/openapi.json",
  "topbarLinks": [
    {
      "name": "Support",
      "url": "mailto:ihsaan@pandan.ai"
    }
  ],
  "topbarCtaButton": {
    "name": "App",
    "url": "https://www.entitymatcher.com"
  },
  "navigation": [
    {
      "group": "Get Started",
      "pages": ["quickstart"]
    },
    {
      "group": "Dataset Endpoints",
      "pages": [
        "api-reference/dataset/get-datasets",
        "api-reference/dataset/upsert-dataset"
      ]
    },
    {
      "group": "Match Endpoints",
      "pages": [
        "api-reference/match/get-all-matches",
        "api-reference/match/get-match-jobs",
        "api-reference/match/get-match-job-status",
        "api-reference/match/match-records",
        "api-reference/match/start-match-job"
      ]
    }
  ]
}
